autogs/_static.py
autogs/util.py
autogs/io/__init__.py
autogs/io/git/__init__.py
autogs/pdf/__init__.py
autogs_core-0.0.1.dist-info/METADATA
autogs_core-0.0.1.dist-info/WHEEL
autogs_core-0.0.1.dist-info/top_level.txt
autogs_core-0.0.1.dist-info/RECORD
