Metadata-Version: 2.1
Name: autogs-core
Version: 0.0.1
Summary: AutoGS Core
Author-email: Younes Strittmatter <ystrittm@gmail.com>
License: MIT License
Project-URL: homepage, http://www.empiricalresearch.ai
Project-URL: repository, https://github.com/AutoResearch/autogs-core
Project-URL: documentation, https://autoresearch.github.io/autogs/
Requires-Python: <4,>=3.10
Requires-Dist: google-cloud-documentai
Requires-Dist: pyPDF2
Requires-Dist: python-dotenv
Requires-Dist: PyGithub
Provides-Extra: build
Requires-Dist: build ; extra == 'build'
Requires-Dist: twine ; extra == 'build'
Requires-Dist: flake8 ; extra == 'build'
Requires-Dist: pre-commit ; extra == 'build'
Provides-Extra: dev
Requires-Dist: autogs-core[test] ; extra == 'dev'
Requires-Dist: autogs-core[build] ; extra == 'dev'
Requires-Dist: autogs-core[notebook] ; extra == 'dev'
Requires-Dist: autogs-core[docs] ; extra == 'dev'
Provides-Extra: docs
Requires-Dist: mkdocs-material ; extra == 'docs'
Requires-Dist: mkdocs-gen-files ; extra == 'docs'
Requires-Dist: mkdocs-literate-nav ; extra == 'docs'
Requires-Dist: mkdocs-section-index ; extra == 'docs'
Requires-Dist: mkdocs-multirepo-plugin ; extra == 'docs'
Requires-Dist: mkdocstrings-python ; extra == 'docs'
Requires-Dist: mkdocs-jupyter ; extra == 'docs'
Requires-Dist: pymdown-extensions ; extra == 'docs'
Provides-Extra: notebook
Requires-Dist: jupyter ; extra == 'notebook'
Requires-Dist: ipython ; extra == 'notebook'
Requires-Dist: ipywidgets ; extra == 'notebook'
Provides-Extra: test
Requires-Dist: pytest ; extra == 'test'
